bpd/__init__.py
bpd/latent_prediction.py
bpd/online_bc.py
bpd/py.typed
bpd/training_utils.py
bpd/agents/__init__.py
bpd/agents/bc.py
bpd/agents/bpd_policy.py
bpd/agents/bpd_trainer.py
bpd/agents/distillation_prediction.py
bpd/agents/gail.py
bpd/agents/ppo.py
bpd/agents/utils.py
bpd/envs/__init__.py
bpd/envs/latent_wrapper.py
bpd/envs/overcooked.py
bpd/envs/pickup_ring.py
bpd/models/__init__.py
bpd/models/overcooked_models.py
bpd/models/pickup_ring_models.py
boltzmann_policy_distribution-0.0.6.dist-info/LICENSE.txt
boltzmann_policy_distribution-0.0.6.dist-info/METADATA
boltzmann_policy_distribution-0.0.6.dist-info/WHEEL
boltzmann_policy_distribution-0.0.6.dist-info/top_level.txt
boltzmann_policy_distribution-0.0.6.dist-info/RECORD
